core/__init__.py
core/config_creator.py
core/config_validator.py
core/utils.py
iot_ccm_config_builder-1.0.0.dist-info/LICENSE.txt
iot_ccm_config_builder-1.0.0.dist-info/METADATA
iot_ccm_config_builder-1.0.0.dist-info/WHEEL
iot_ccm_config_builder-1.0.0.dist-info/top_level.txt
iot_ccm_config_builder-1.0.0.dist-info/RECORD
