Metadata-Version: 2.1
Name: iot-ccm-config-builder
Version: 1.0.0
Summary: A tool to build config files for the IOT CCM SDK project
Home-page: https://gitlab.com/prometheuscomputing/nist-ssd-iot-testbed/iot-ccm-config-builder
Author: NIST IT Lab
Author-email: itl_inquiries@nist.gov
License: UNKNOWN
Platform: UNKNOWN
Requires-Dist: jsonschema (==3.2.0)
